peptide/__init__.py
peptide/architecture.s.HTML
peptide/module.MD
peptide/module.s.HTML
peptide/__agenda/maybes.s.HTML
peptide/__agenda/priorities.s.HTML
peptide/__agenda/processes/errout/script.py
peptide/__agenda/processes/errout/start.py
peptide/__agenda/processes/errout_v1/script.py
peptide/__agenda/processes/errout_v1/start.py
peptide/__agenda/processes/errout_v2/script.py
peptide/__agenda/processes/errout_v2/start.py
peptide/__license/license.s.HTML
peptide/_book/advanced tutorial.s.HTML
peptide/_book/book.s.HTML
peptide/_book/example output.s.HTML
peptide/_book/relevant.s.HTML
peptide/_clique/__init__.py
peptide/_clique/group/__init__.py
peptide/_status/establish.py
peptide/_status/status.proc.py
peptide/_status/status.s.HTML
peptide/_status/status_py.py
peptide/_status/DB/records.json
peptide/_status/monitors/-1_start/status_1.py
peptide/_status/monitors/-1_start/chassis/modules/monitor_1.py
peptide/_status/monitors/0_start/status_1.py
peptide/_status/monitors/0_start/chassis/modules/monitor_1.py
peptide/_status/monitors/1/status_1.py
peptide/_status/monitors/1/stasis/path_1_health.py
peptide/_status/monitors/1/stasis/path_2_health.py
peptide/_status/monitors/2/status_1.py
peptide/_status/monitors/2/stasis/1_health.py
peptide/_status/monitors/2/stasis/2_health.py
peptide/_status/monitors/2/stasis/modules/MODULE_1.py
peptide/_status/monitors/3_empty_glob/status_1.py
peptide/_status/monitors/4_bad_import/status_1.py
peptide/_status/monitors/4_bad_import/stasis/1_health.py
peptide/_status/monitors/5__file__/status_1.py
peptide/_status/monitors/5__file__/stasis/1_health.py
peptide/_status/monitors/5__file__/stasis/MODULES/MODULE_1.py
peptide/_status/monitors/6_various/status_1.py
peptide/_status/monitors/6_various/stasis/1_health.py
peptide/_status/monitors/6_various/stasis/2_health.py
peptide/_status/monitors/6_various/stasis/3_health.py
peptide/_status/monitors/6_various/stasis/MODULES/MODULE_1.py
peptide/_status/monitors/7/status_1.py
peptide-1.0.2.dist-info/METADATA
peptide-1.0.2.dist-info/WHEEL
peptide-1.0.2.dist-info/entry_points.txt
peptide-1.0.2.dist-info/top_level.txt
peptide-1.0.2.dist-info/RECORD
